Risc-V_Processor/ALU/ALU.v
module ALU (
    input [3:0] in1, in2, 
    input [3:0] alu_control,
    output reg [3:0] alu_result,
    output reg zero_flag
);
    always @(*)
    begin
        // Operating based on control input
        case(alu_control)
            4'b0000: alu_result = in1 & in2;   // AND
            4'b0001: alu_result = in1 | in2;   // OR
            4'b0010: alu_result = in1 + in2;   // ADD
            4'b0100: alu_result = in1 - in2;   // SUB
            4'b1000: alu_result = (in1 < in2) ? 4'b0001 : 4'b0000; // SLT
            4'b0011: alu_result = in1 << in2[1:0]; // SLL (limited shift)
            4'b0101: alu_result = in1 >> in2[1:0]; // SRL (limited shift)
            4'b0110: alu_result = in1 * in2;   // MUL
            4'b0111: alu_result = in1 ^ in2;   // XOR
            default: alu_result = 4'b0000; // Default case
        endcase

        // Setting Zero_flag if ALU_result is zero
        zero_flag = (alu_result == 4'b0000) ? 1'b1 : 1'b0;
    end
endmodule

Risc-V_Processor/Project/ALU_testbench.v
module ALU_testbench ();
    reg [3:0] A, B;
    reg [3:0] ALUControl;
    wire ZERO;
    wire [3:0] ALUResult;

    // Instantiating ALU module
    ALU ALU_module(.in1(A), .in2(B), .alu_control(ALUControl), .zero_flag(ZERO), .alu_result(ALUResult));

    // Setting up waveform
    initial
    begin
        $dumpfile("output_wave.vcd");
        $dumpvars(0, ALU_testbench);
    end
    

    // Monitoring changing values
    initial
    $monitor($time, "\nInput_1 = %b, \nInput_2 = %b,\nALU_control = %b,\n ALU_result = %b, Zero_flag = %b\n", A, B, ALUControl, ALUResult, ZERO);

    // Test conditions
    initial
    begin
        A = 4'b0011; B = 4'b1010; ALUControl = 4'b0000;
    #20 A = 4'b0011; B = 4'b1010; ALUControl = 4'b0001;
    #20 A = 4'b0011; B = 4'b0001; ALUControl = 4'b0010;
    #20 A = 4'b1010; B = 4'b0011; ALUControl = 4'b0100;
    #20 A = 4'b0011; B = 4'b0110; ALUControl = 4'b1000;
    #20 A = 4'b0110; B = 4'b0010; ALUControl = 4'b0011;
    #20 A = 4'b0110; B = 4'b0010; ALUControl = 4'b0101;
    #20 A = 4'b0011; B = 4'b0001; ALUControl = 4'b0110;
    #20 A = 4'b1010; B = 4'b0101; ALUControl = 4'b0111;
    end

    // Finish after 180 time units
    initial
    #180 $finish;

endmodule

Risc-V_Processor/ALU/output_wave.vcd
$date
	Fri Mar  7 13:11:01 2025
$end
$version
	Icarus Verilog
$end
$timescale
	1s
$end
$scope module ALU_testbench $end
$var wire 1 ! ZERO $end
$var wire 4 " ALUResult [3:0] $end
$var reg 4 # A [3:0] $end
$var reg 4 $ ALUControl [3:0] $end
$var reg 4 % B [3:0] $end
$scope module ALU_module $end
$var wire 4 & alu_control [3:0] $end
$var wire 4 ' in1 [3:0] $end
$var wire 4 ( in2 [3:0] $end
$var reg 4 ) alu_result [3:0] $end
$var reg 1 ! zero_flag $end
$upscope $end
$upscope $end
$enddefinitions $end
$comment Show the parameter values. $end
$dumpall
$end
#0
$dumpvars
b10 )
b1010 (
b11 '
b0 &
b1010 %
b0 $
b11 #
b10 "
0!
$end
#20
b1011 "
b1011 )
b1 $
b1 &
#40
b100 "
b100 )
b10 $
b10 &
b1 %
b1 (
#60
b111 "
b111 )
b100 $
b100 &
b11 %
b11 (
b1010 #
b1010 '
#80
b1 "
b1 )
b1000 $
b1000 &
b110 %
b110 (
b11 #
b11 '
#100
b1000 "
b1000 )
b11 $
b11 &
b10 %
b10 (
b110 #
b110 '
#120
b1 "
b1 )
b101 $
b101 &
#140
b11 "
b11 )
b110 $
b110 &
b1 %
b1 (
b11 #
b11 '
#160
b1111 "
b1111 )
b111 $
b111 &
b101 %
b101 (
b1010 #
b1010 '
